rottnest-1.5.0.dist-info/METADATA
rottnest-1.5.0.dist-info/WHEEL
rottnest/nlp.py
rottnest/internal.py
rottnest/__init__.py
rottnest/utils.py
rottnest/table.py
rottnest/rottnest.abi3.so
rottnest-1.5.0.dist-info/RECORD
