Metadata-Version: 2.1
Name: rottnest
Version: 1.5.0
Classifier: Programming Language :: Rust
Classifier: Programming Language :: Python :: Implementation :: CPython
Classifier: Programming Language :: Python :: Implementation :: PyPy
Requires-Dist: pyarrow
Requires-Dist: polars
Requires-Dist: tqdm
Requires-Dist: boto3
Requires-Dist: getdaft
Requires-Dist: duckdb ; extra == 'bm25'
Requires-Dist: openai ; extra == 'bm25'
Requires-Dist: FlagEmbedding ; extra == 'bm25'
Provides-Extra: bm25
Requires-Python: >=3.7
